aaindex/__init__.py
aaindex/aaindex1.py
aaindex/aaindex2.py
aaindex/aaindex3.py
aaindex/data/README.md
aaindex/data/aaindex1
aaindex/data/aaindex1.json
aaindex/data/aaindex2
aaindex/data/aaindex3
aaindex/data/aaindex_categories.txt
aaindex/data/aaindex_to_category.txt
tests/__init__.py
tests/test_aaindex1.py
tests/test_aaindex2.py
tests/test_aaindex3.py
aaindex-1.1.2.dist-info/LICENSE
aaindex-1.1.2.dist-info/METADATA
aaindex-1.1.2.dist-info/WHEEL
aaindex-1.1.2.dist-info/top_level.txt
aaindex-1.1.2.dist-info/zip-safe
aaindex-1.1.2.dist-info/RECORD
