Metadata-Version: 2.1
Name: aaindex
Version: 1.1.2
Summary: A lightweight Python software package for accessing the data in the various AAIndex databases, which represent the physiochemical, biochemical and structural properties of amino acids as numerical indices.
Home-page: https://github.com/amckenna41/aaindex
Author: AJ McKenna: https://github.com/amckenna41
Author-email: amckenna41@qub.ac.uk
Maintainer: AJ McKenna
License: MIT
Download-URL: https://github.com/amckenna41/aaindex/archive/refs/heads/main.zip
Keywords: amino acid index,aaindex,bioinformatics,protein engineering,python,pypi,physiochemical properties,biochemical properties,proteins,protein structure prediction,pysar
Platform: UNKNOWN
Classifier: Development Status :: 5 - Production/Stable
Classifier: Environment :: Console
Classifier: Intended Audience :: Developers
Classifier: Intended Audience :: Science/Research
Classifier: Intended Audience :: Healthcare Industry
Classifier: Intended Audience :: Information Technology
Classifier: License :: OSI Approved :: MIT License
Classifier: Natural Language :: English
Classifier: Programming Language :: Python :: 3.8
Classifier: Programming Language :: Python :: 3.9
Classifier: Programming Language :: Python :: 3.10
Classifier: Programming Language :: Python :: Implementation :: PyPy
Classifier: Programming Language :: Python :: 3 :: Only
Classifier: Programming Language :: Python :: Implementation :: PyPy
Classifier: Topic :: Scientific/Engineering :: Bio-Informatics
Classifier: Topic :: Scientific/Engineering :: Medical Science Apps.
Classifier: Topic :: Scientific/Engineering :: Mathematics
Classifier: Topic :: Software Development :: Libraries :: Python Modules
Requires-Python: >=3.8
Provides-Extra: docs
Requires-Dist: sphinx ; extra == 'docs'
Provides-Extra: test
Requires-Dist: pytest ; extra == 'test'
Requires-Dist: pytest-cov ; extra == 'test'
Requires-Dist: pytest-flake8 ; extra == 'test'
Requires-Dist: pytest-timeout ; extra == 'test'
